{
  "warnings" : [ ],
  "files" : [ "report.json" ],
  "info" : {
    "cfgs" : "7",
    "duration" : "124ms",
    "end" : "2023-05-08T17:36:56.913+02:00",
    "expressions" : "566",
    "files" : "0",
    "globals" : "14",
    "members" : "58",
    "programs" : "1",
    "start" : "2023-05-08T17:36:56.789+02:00",
    "statements" : "151",
    "units" : "17",
    "version" : "0.1b8",
    "warnings" : "0"
  },
  "configuration" : {
    "analysisGraphs" : "NONE",
    "descendingPhaseType" : "NONE",
    "dumpForcesUnwinding" : "false",
    "fixpointWorkingSet" : "DuplicateFreeFIFOWorkingSet",
    "glbThreshold" : "5",
    "hotspots" : "unset",
    "jsonOutput" : "true",
    "openCallPolicy" : "RelaxedOpenCallPolicy",
    "optimize" : "false",
    "recursionWideningThreshold" : "5",
    "semanticChecks" : "IntegrityNIChecker",
    "serializeInputs" : "false",
    "serializeResults" : "false",
    "syntacticChecks" : "",
    "wideningThreshold" : "5",
    "workdir" : "go-outputs/cc/chaincode"
  }
}