{"name":"untyped main::typeSwitch1()","description":null,"nodes":[{"id":0,"subNodes":[1,2],"text":"var i interface{} = \"hello\""},{"id":1,"text":"i"},{"id":2,"text":"\"hello\""},{"id":3,"text":"v, ok := .(int)(i)"},{"id":4,"text":"v"},{"id":5,"text":"ok"},{"id":6,"subNodes":[21],"text":".(int)(i)"},{"id":8,"subNodes":[9,10],"text":"==(ok, true)"},{"id":9,"text":"ok"},{"id":10,"text":"true"},{"id":11,"subNodes":[12,13,14],"text":"fmt::Printf(\"Twice %v is %v\\n\", v, *(v, 2))"},{"id":12,"text":"\"Twice %v is %v\\n\""},{"id":13,"text":"v"},{"id":14,"subNodes":[15,16],"text":"*(v, 2)"},{"id":15,"text":"v"},{"id":16,"text":"2"},{"id":17,"text":"v, ok := .(string)(i)"},{"id":18,"text":"v"},{"id":19,"text":"ok"},{"id":20,"subNodes":[21],"text":".(string)(i)"},{"id":21,"text":"i"},{"id":22,"subNodes":[23,24],"text":"==(ok, true)"},{"id":23,"text":"ok"},{"id":24,"text":"true"},{"id":25,"subNodes":[26,27,28],"text":"fmt::Printf(\"%q is %v bytes long\\n\", v, len(v))"},{"id":26,"text":"\"%q is %v bytes long\\n\""},{"id":27,"text":"v"},{"id":28,"subNodes":[29],"text":"len(v)"},{"id":29,"text":"v"},{"id":30,"subNodes":[31,32],"text":"fmt::Printf(\"I don't know about type %T!\\n\", v)"},{"id":31,"text":"\"I don't know about type %T!\\n\""},{"id":32,"text":"v"},{"id":33,"text":"ret"}],"edges":[{"sourceId":0,"destId":3,"kind":"SequentialEdge"},{"sourceId":3,"destId":8,"kind":"SequentialEdge"},{"sourceId":8,"destId":11,"kind":"TrueEdge"},{"sourceId":8,"destId":17,"kind":"FalseEdge"},{"sourceId":11,"destId":33,"kind":"SequentialEdge"},{"sourceId":17,"destId":22,"kind":"SequentialEdge"},{"sourceId":22,"destId":25,"kind":"TrueEdge"},{"sourceId":22,"destId":30,"kind":"FalseEdge"},{"sourceId":25,"destId":33,"kind":"SequentialEdge"},{"sourceId":30,"destId":33,"kind":"SequentialEdge"}],"descriptions":[]}